README.txt
setup.cfg
setup.py
docs/HISTORY.txt
emencia/__init__.py
emencia.django.repozewho.egg-info/PKG-INFO
emencia.django.repozewho.egg-info/SOURCES.txt
emencia.django.repozewho.egg-info/dependency_links.txt
emencia.django.repozewho.egg-info/entry_points.txt
emencia.django.repozewho.egg-info/namespace_packages.txt
emencia.django.repozewho.egg-info/not-zip-safe
emencia.django.repozewho.egg-info/requires.txt
emencia.django.repozewho.egg-info/top_level.txt
emencia/django/__init__.py
emencia/django/repozewho/__init__.py
emencia/django/repozewho/middleware.py
emencia/django/repozewho/repozeplugin.py
emencia/django/repozewho/tests.py