Metadata-Version: 1.0
Name: emencia.django.repozewho
Version: 0.2
Summary: Django app for use repoze.who for autentication
Home-page: UNKNOWN
Author: lafaye philippe
Author-email: lafaye@emencia.com
License: GPLv3
Platform: UNKNOWN
Classifier: Programming Language :: Python
Classifier: Topic :: Software Development :: Libraries :: Python Modules
